iqrfpy/ext/diagnostics/__init__.py
iqrfpy/ext/diagnostics/constants.py
iqrfpy/ext/diagnostics/diagnostics.py
iqrfpy/ext/diagnostics/exceptions.py
iqrfpy/ext/diagnostics/objects.py
iqrfpy/ext/diagnostics/py.typed
iqrfpy_diagnostics-0.1.1.dist-info/LICENSE
iqrfpy_diagnostics-0.1.1.dist-info/METADATA
iqrfpy_diagnostics-0.1.1.dist-info/WHEEL
iqrfpy_diagnostics-0.1.1.dist-info/top_level.txt
iqrfpy_diagnostics-0.1.1.dist-info/RECORD
