Metadata-Version: 2.1
Name: iqrfpy-diagnostics
Version: 0.1.1
Summary: Diagnostics for iqrfpy
Home-page: https://gitlab.iqrf.org/open-source/iqrf-sdk/iqrfpy/iqrfpy-diagnostics
Author: Karel Hanák
Author-email: karel.hanak@iqrf.org
License: Apache-2.0
Project-URL: Homepage, https://gitlab.iqrf.org/open-source/iqrf-sdk/iqrfpy/iqrfpy-diagnostics
Project-URL: Changelog, https://gitlab.iqrf.org/open-source/iqrf-sdk/iqrfpy/iqrfpy-diagnostics/-/blob/master/changelog.md
Project-URL: Source code, https://gitlab.iqrf.org/open-source/iqrf-sdk/iqrfpy/iqrfpy-diagnostics
Project-URL: Issue tracker, https://gitlab.iqrf.org/open-source/iqrf-sdk/iqrfpy/iqrfpy-diagnostics/-/issues
Keywords: iqrf
Classifier: Development Status :: 4 - Beta
Classifier: License :: OSI Approved :: Apache Software License
Classifier: Programming Language :: Python
Classifier: Programming Language :: Python :: 3
Classifier: Programming Language :: Python :: 3.10
Classifier: Programming Language :: Python :: 3.11
Classifier: Programming Language :: Python :: 3.12
Classifier: Operating System :: Microsoft :: Windows
Classifier: Operating System :: POSIX
Classifier: Operating System :: Unix
Classifier: Operating System :: MacOS
Requires-Python: >=3.10
License-File: LICENSE
Requires-Dist: iqrfpy >=0.2.0
Requires-Dist: tabulate >=0.9.0
